pi_ai_os.py
pi_ai_os-0.0.4.dist-info/LICENSE
pi_ai_os-0.0.4.dist-info/METADATA
pi_ai_os-0.0.4.dist-info/WHEEL
pi_ai_os-0.0.4.dist-info/entry_points.txt
pi_ai_os-0.0.4.dist-info/RECORD
