Metadata-Version: 2.1
Name: pi-ai-os
Version: 0.0.4
Summary: Integrate your OS with an LLM.
License: Apache 2.0
Author: piEsposito
Author-email: piero.skywalker@gmail.com
Requires-Python: >=3.12,<4.0
Classifier: License :: Other/Proprietary License
Classifier: Programming Language :: Python :: 3
Classifier: Programming Language :: Python :: 3.12
Requires-Dist: omegaconf (>=2.3.0,<3.0.0)
Requires-Dist: pillow (>=10.4.0,<11.0.0)
Requires-Dist: tiny-ai-client (>=0.0.11,<0.0.12)
